<?xml version="1.0" encoding="iso-8859-1"?>
<!DOCTYPE muclient>
<!-- Saved on 2016年 八月 20日 星期六, 下午 4:41 -->
<!-- MuClient version 4.94 -->
<!-- Written by Nick Gammon -->
<!-- Home Page: http://www.mushclient.com/ -->

<!-- 插件状态已被保存。插件:“main_window”，游戏:“jnxkx”。 -->

<muclient>

<!-- variables -->

<variables
   muclient_version="4.94"
   world_file_version="15"
   date_saved="2016-08-20 16:41:58"
  >
  <variable name="enabled">true</variable>
  <variable name="trbottom">486</variable>
  <variable name="trleft">7</variable>
  <variable name="trright">899</variable>
  <variable name="trtop">131</variable>
</variables>
</muclient>
